deepeval/__init__.py
deepeval/_version.py
deepeval/annotation/__init__.py
deepeval/annotation/annotation.py
deepeval/annotation/api.py
deepeval/anthropic/__init__.py
deepeval/anthropic/extractors.py
deepeval/anthropic/patch.py
deepeval/anthropic/utils.py
deepeval/benchmarks/__init__.py
deepeval/benchmarks/arc/__init__.py
deepeval/benchmarks/arc/arc.py
deepeval/benchmarks/arc/mode.py
deepeval/benchmarks/arc/template.py
deepeval/benchmarks/base_benchmark.py
deepeval/benchmarks/bbq/__init__.py
deepeval/benchmarks/bbq/bbq.py
deepeval/benchmarks/bbq/task.py
deepeval/benchmarks/bbq/template.py
deepeval/benchmarks/big_bench_hard/__init__.py
deepeval/benchmarks/big_bench_hard/big_bench_hard.py
deepeval/benchmarks/big_bench_hard/cot_prompts/__init__.py
deepeval/benchmarks/big_bench_hard/cot_prompts/boolean_expressions.txt
deepeval/benchmarks/big_bench_hard/cot_prompts/causal_judgement.txt
deepeval/benchmarks/big_bench_hard/cot_prompts/date_understanding.txt
deepeval/benchmarks/big_bench_hard/cot_prompts/disambiguation_qa.txt
deepeval/benchmarks/big_bench_hard/cot_prompts/dyck_languages.txt
deepeval/benchmarks/big_bench_hard/cot_prompts/formal_fallacies.txt
deepeval/benchmarks/big_bench_hard/cot_prompts/geometric_shapes.txt
deepeval/benchmarks/big_bench_hard/cot_prompts/hyperbaton.txt
deepeval/benchmarks/big_bench_hard/cot_prompts/logical_deduction_five_objects.txt
deepeval/benchmarks/big_bench_hard/cot_prompts/logical_deduction_seven_objects.txt
deepeval/benchmarks/big_bench_hard/cot_prompts/logical_deduction_three_objects.txt
deepeval/benchmarks/big_bench_hard/cot_prompts/movie_recommendation.txt
deepeval/benchmarks/big_bench_hard/cot_prompts/multistep_arithmetic_two.txt
deepeval/benchmarks/big_bench_hard/cot_prompts/navigate.txt
deepeval/benchmarks/big_bench_hard/cot_prompts/object_counting.txt
deepeval/benchmarks/big_bench_hard/cot_prompts/penguins_in_a_table.txt
deepeval/benchmarks/big_bench_hard/cot_prompts/reasoning_about_colored_objects.txt
deepeval-3.8.3.dist-info/LICENSE.md
deepeval-3.8.3.dist-info/METADATA
deepeval-3.8.3.dist-info/WHEEL
deepeval-3.8.3.dist-info/entry_points.txt
deepeval-3.8.3.dist-info/RECORD
