Metadata-Version: 2.1
Name: deepeval
Version: 3.8.3
Summary: The LLM Evaluation Framework
Home-page: https://github.com/confident-ai/deepeval
License: Apache-2.0
Author: Jeffrey Ip
Author-email: jeffreyip@confident-ai.com
Requires-Python: >=3.9,<4.0
Classifier: License :: OSI Approved :: Apache Software License
Classifier: Programming Language :: Python :: 3
Classifier: Programming Language :: Python :: 3.9
Classifier: Programming Language :: Python :: 3.10
Classifier: Programming Language :: Python :: 3.11
Requires-Dist: aiohttp
Requires-Dist: click (>=8.0.0,<8.3.0)
Requires-Dist: grpcio (>=1.67.1,<2.0.0)
Requires-Dist: jinja2
Requires-Dist: nest_asyncio
Requires-Dist: openai
Requires-Dist: opentelemetry-api (>=1.24.0,<2.0.0)
Requires-Dist: opentelemetry-exporter-otlp-proto-grpc (>=1.24.0,<2.0.0)
Requires-Dist: opentelemetry-sdk (>=1.24.0,<2.0.0)
Requires-Dist: portalocker
Requires-Dist: posthog (>=5.4.0,<6.0.0)
Requires-Dist: pydantic (>=2.11.7,<3.0.0)
Requires-Dist: pydantic-settings (>=2.10.1,<3.0.0)
Requires-Dist: pyfiglet
Requires-Dist: pytest
Requires-Dist: pytest-asyncio
Requires-Dist: pytest-repeat
Requires-Dist: pytest-rerunfailures
Requires-Dist: pytest-xdist
Requires-Dist: python-dotenv (>=1.1.1,<2.0.0)
Requires-Dist: requests (>=2.31.0,<3.0.0)
Requires-Dist: rich (>=13.6.0,<15.0.0)
Requires-Dist: sentry-sdk
Requires-Dist: setuptools
Requires-Dist: tabulate (>=0.9.0,<0.10.0)
Requires-Dist: tenacity (>=8.0.0,<=10.0.0)
Requires-Dist: tqdm (>=4.66.1,<5.0.0)
Requires-Dist: typer (>=0.9,<1.0.0)
Requires-Dist: wheel
Project-URL: Documentation, https://deepeval.com
Project-URL: Repository, https://github.com/confident-ai/deepeval
